amcess/__init__.py
amcess/ascec.py
amcess/base_molecule.py
amcess/electronic_energy.py
amcess/gaussian_process.py
amcess/search_engine.py
amcess/data/__init__.py
amcess/data/atomic_data.py
amcess-0.1.1.dist-info/LICENSE
amcess-0.1.1.dist-info/METADATA
amcess-0.1.1.dist-info/WHEEL
amcess-0.1.1.dist-info/top_level.txt
amcess-0.1.1.dist-info/RECORD
