Metadata-Version: 2.1
Name: amcess
Version: 0.1.1
Summary: Atomic and Molecular Cluster Energy Surface Sampler
Home-page: https://gitlab.com/ADanianZE/amcess
Author: 
Author-email: 
License: The GPLv3 License
Keywords: Atomic Cluster,Molecular Cluster,optimization,Potential Energy Surface,PES,Monte Carlo,Simulated Annealing,Bayesian Optimization
Platform: UNKNOWN
Classifier: Development Status :: 4 - Beta
Classifier: Intended Audience :: Education
Classifier: Intended Audience :: Science/Research
Classifier: License :: OSI Approved :: GNU General Public License v3 (GPLv3)
Classifier: Operating System :: OS Independent
Classifier: Programming Language :: Python
Classifier: Programming Language :: Python :: 3.8
Classifier: Programming Language :: Python :: Implementation :: CPython
Classifier: Topic :: Scientific/Engineering
Requires-Dist: GPyOpt (==1.2.6)
Requires-Dist: attrs (==21.2)
Requires-Dist: geomeTRIC (==0.9.7.2)
Requires-Dist: h5py (==3.1.0)
Requires-Dist: matplotlib (==3.4.2)
Requires-Dist: numpy (==1.21.2)
Requires-Dist: pyDOE (==0.3.8)
Requires-Dist: pyberny (==0.6.3)
Requires-Dist: pyscf (==1.7.6.post1)
Requires-Dist: scipy (==1.7.1)
